ipypixano/__init__.py
ipypixano/_frontend.py
ipypixano/_version.py
ipypixano/widget.py
ipypixano/labextension/build_log.json
ipypixano/labextension/package.json
ipypixano/labextension/static/_84ac-_4434-_126c-_0a64-_2348-_0754-_4b970.c4b3608fa2188c1b13f0.js
ipypixano/labextension/static/_84ac-_4434-_126c-_0a64-_2348-_0754-_4b970.c4b3608fa2188c1b13f0.js.map
ipypixano/labextension/static/_84ac-_4434-_126c-_0a64-_2348-_0754-_4b971.48ba207eef20234cb0b3.js
ipypixano/labextension/static/_84ac-_4434-_126c-_0a64-_2348-_0754-_4b971.48ba207eef20234cb0b3.js.map
ipypixano/labextension/static/lib_index_js.d8d74e1e766335db5a91.js
ipypixano/labextension/static/lib_index_js.d8d74e1e766335db5a91.js.map
ipypixano/labextension/static/lib_plugin_js.cdea264c926891729df5.js
ipypixano/labextension/static/lib_plugin_js.cdea264c926891729df5.js.map
ipypixano/labextension/static/lib_widget_js.4f34811bfebbbb732999.js
ipypixano/labextension/static/lib_widget_js.4f34811bfebbbb732999.js.map
ipypixano/labextension/static/lib_widget_js.a8fe0fa32ee07f1e7f9e.js
ipypixano/labextension/static/lib_widget_js.a8fe0fa32ee07f1e7f9e.js.map
ipypixano/labextension/static/lib_widget_js.c6de23eb073fa2004b4e.js
ipypixano/labextension/static/lib_widget_js.c6de23eb073fa2004b4e.js.map
ipypixano/labextension/static/lib_widget_js.d45bff9897406b15c1e2.js
ipypixano/labextension/static/lib_widget_js.d45bff9897406b15c1e2.js.map
ipypixano/labextension/static/lib_widget_js.e9752dab0ee3b38028e5.js
ipypixano/labextension/static/lib_widget_js.e9752dab0ee3b38028e5.js.map
ipypixano/labextension/static/node_modules_material_dom_keyboard_js-node_modules_material_list_constants_js-node_modules_ma-ea0e71.4278f59dd6b9aa6eaf61.js
ipypixano/labextension/static/node_modules_material_dom_keyboard_js-node_modules_material_list_constants_js-node_modules_ma-ea0e71.4278f59dd6b9aa6eaf61.js.map
ipypixano/labextension/static/node_modules_material_mwc-base_form-element_js-node_modules_material_mwc-base_observer_js.f975b3c682c9a43786a3.js
ipypixano-0.1.9.dist-info/LICENSE.txt
ipypixano-0.1.9.dist-info/METADATA
ipypixano-0.1.9.dist-info/WHEEL
ipypixano-0.1.9.dist-info/top_level.txt
ipypixano-0.1.9.dist-info/RECORD
